metanetmap/__init__.py
metanetmap/build_database.py
metanetmap/cli.py
metanetmap/mapping.py
metanetmap/utils.py
metanetmap/toys_tests_data/conversion_datatable_toys.tsv
metanetmap/toys_tests_data/toys/maf/toys1.tsv
metanetmap/toys_tests_data/toys/maf/toys2.tsv
metanetmap/toys_tests_data/toys/maf/toys3.tsv
metanetmap/toys_tests_data/toys/sbml/toys1.sbml
metanetmap/toys_tests_data/toys/sbml/toys2.sbml
metanetmap/toys_tests_data/toys/sbml/toys3.xml
metanetmap-1.1.2.dist-info/licenses/AUTHORS.rst
metanetmap-1.1.2.dist-info/licenses/LICENSE
metanetmap-1.1.2.dist-info/METADATA
metanetmap-1.1.2.dist-info/WHEEL
metanetmap-1.1.2.dist-info/entry_points.txt
metanetmap-1.1.2.dist-info/top_level.txt
metanetmap-1.1.2.dist-info/RECORD
