Metadata-Version: 2.4
Name: metanetmap
Version: 1.1.2
Summary: A Python package for mapping metabolites between metabolic models and  metabolomics data.
Author-email: Coralie Muller <coralie.muller@inria.fr>, Clémence Frioux <clemence.frioux@inria.fr>, Sylvain Prigent <sylvain.prigent@inrae.fr>
Maintainer-email: Coralie Muller <coralie.muller@inria.fr>
License: GNU General Public License v3
Project-URL: homepage, https://gitlab.inria.fr/mistic/mnm
License-File: LICENSE
License-File: AUTHORS.rst
Requires-Dist: setuptools
Requires-Dist: cobra
Requires-Dist: numpy
Requires-Dist: pandas
Requires-Dist: aiohttp
Requires-Dist: tqdm
Provides-Extra: dev
Requires-Dist: coverage; extra == "dev"
Requires-Dist: mypy; extra == "dev"
Requires-Dist: pytest; extra == "dev"
Requires-Dist: ruff; extra == "dev"
Dynamic: license-file
